MLContainers
