Metadata-Version: 2.1
Name: MLContainers
Version: 1.0.1
Summary: Collection of Modular, Reusable ML Pipeline Components
Home-page: https://github.com/robertfrankzhang/MLContainers
Author: Robert F. Zhang
Author-email: robertzhang100@gmail.com, robertzh@wharton.upenn.edu
License: License :: OSI Approved :: GNU General Public License v3 (GPLv3)
Download-URL: https://github.com/robertfrankzhang/MLContainers/archive/v_1.0.tar.gz
Keywords: machine learning,data analysis,data science
Platform: UNKNOWN
Classifier: Development Status :: 5 - Production/Stable
Classifier: Intended Audience :: Science/Research
Classifier: Topic :: Utilities
Classifier: License :: OSI Approved :: GNU General Public License v3 (GPLv3)
Classifier: Programming Language :: Python :: 3
Classifier: Programming Language :: Python :: 3.4
Classifier: Programming Language :: Python :: 3.5
Classifier: Programming Language :: Python :: 3.6
Classifier: Programming Language :: Python :: 3.7
